glossbert/__init__.py
glossbert/glossbert.py
glossbert-1.0.6.dist-info/LICENSE
glossbert-1.0.6.dist-info/METADATA
glossbert-1.0.6.dist-info/WHEEL
glossbert-1.0.6.dist-info/top_level.txt
glossbert-1.0.6.dist-info/RECORD
