Metadata-Version: 2.1
Name: glossbert
Version: 1.0.6
Summary: Python package for Word Sentence Disambiguation (WSD) using GlossBERT model and NLTK WordNet.
Author-email: José María Cruz Lorite <josemariacruzlorite@gmail.com>
Project-URL: Homepage, https://github.com/cruzlorite/glossbert
Classifier: Programming Language :: Python :: 3
Classifier: License :: OSI Approved :: MIT License
Classifier: Operating System :: OS Independent
Requires-Python: >=3.9
License-File: LICENSE
Requires-Dist: torch
Requires-Dist: transformers
Requires-Dist: nltk
